oarepo_vocabularies_basic/__init__.py
oarepo_vocabularies_basic/config.py
oarepo_vocabularies_basic/ext.py
oarepo_vocabularies_basic/proxies.py
oarepo_vocabularies_basic/version.py
oarepo_vocabularies_basic/views.py
oarepo_vocabularies_basic/records/__init__.py
oarepo_vocabularies_basic/records/api.py
oarepo_vocabularies_basic/records/dumper.py
oarepo_vocabularies_basic/records/models.py
oarepo_vocabularies_basic/records/jsonschemas/__init__.py
oarepo_vocabularies_basic/records/jsonschemas/oarepo-vocabularies-basic-1.0.0.json
oarepo_vocabularies_basic/records/mappings/__init__.py
oarepo_vocabularies_basic/records/mappings/v7/__init__.py
oarepo_vocabularies_basic/records/mappings/v7/oarepo_vocabularies_basic/__init__.py
oarepo_vocabularies_basic/records/mappings/v7/oarepo_vocabularies_basic/oarepo-vocabularies-basic-1.0.0.json
oarepo_vocabularies_basic/resources/__init__.py
oarepo_vocabularies_basic/resources/config.py
oarepo_vocabularies_basic/resources/resource.py
oarepo_vocabularies_basic/services/__init__.py
oarepo_vocabularies_basic/services/config.py
oarepo_vocabularies_basic/services/facets.py
oarepo_vocabularies_basic/services/permissions.py
oarepo_vocabularies_basic/services/schema.py
oarepo_vocabularies_basic/services/search.py
oarepo_vocabularies_basic/services/service.py
oarepo_vocabularies_basic-0.0.15.dist-info/METADATA
oarepo_vocabularies_basic-0.0.15.dist-info/WHEEL
oarepo_vocabularies_basic-0.0.15.dist-info/entry_points.txt
oarepo_vocabularies_basic-0.0.15.dist-info/top_level.txt
oarepo_vocabularies_basic-0.0.15.dist-info/RECORD
